{
  "git_hash": "5a604394",
  "timestamp": "2026-07-16T17:30:52",
  "version": "1.4.0",
  "params": {
    "nelx": 50,
    "nely": 50,
    "ft": 2,
    "E0": 199.0,
    "Emin": 1e-09,
    "nu": 0.3,
    "max_iter": 150,
    "tol_change": 0.01,
    "tol_obj": 0.05,
    "window_size": 20,
    "save_every": 9999,
    "scale_factor": 1,
    "verbose": false,
    "volfrac": 0.506942,
    "penal": 2.774405,
    "rmin": 1.075622,
    "move": 0.166453,
    "void_size_frac": 0.399465,
    "seed": "square",
    "objective": "auxetic"
  }
}